<?xml version="1.0" standalone="yes"?>
<NewDataSet>
  <xs:schema id="NewDataSet" xmlns="" xmlns:xs="http://www.w3.org/2001/XMLSchema" xmlns:msdata="urn:schemas-microsoft-com:xml-msdata">
    <xs:element name="NewDataSet" msdata:IsDataSet="true" msdata:Locale="de-DE">
      <xs:complexType>
        <xs:choice minOccurs="0" maxOccurs="unbounded">
          <xs:element name="Table">
            <xs:complexType>
              <xs:sequence>
                <xs:element name="Stapel" type="xs:int" minOccurs="0" />
                <xs:element name="Name" type="xs:string" minOccurs="0" />
                <xs:element name="Vorname" type="xs:string" minOccurs="0" />
                <xs:element name="Geburtsort" type="xs:string" minOccurs="0" />
                <xs:element name="Bogennummer" type="xs:string" minOccurs="0" />
                <xs:element name="Teil1_schriftlich" type="xs:string" minOccurs="0" />
                <xs:element name="Teil2_schriftlich" type="xs:string" minOccurs="0" />
                <xs:element name="Teil3_schriftlich" type="xs:string" minOccurs="0" />
                <xs:element name="Teil4_schriftlich" type="xs:string" minOccurs="0" />
                <xs:element name="BewertSchriftlich" type="xs:string" minOccurs="0" />
                <xs:element name="Teil1_muendlich" type="xs:string" minOccurs="0" />
                <xs:element name="Teil2_muendlich" type="xs:string" minOccurs="0" />
                <xs:element name="Teil3_muendlich" type="xs:string" minOccurs="0" />
                <xs:element name="Teil4_muendlich" type="xs:string" minOccurs="0" />
                <xs:element name="Teil5_muendlich" type="xs:string" minOccurs="0" />
                <xs:element name="BewertMuendlich" type="xs:string" minOccurs="0" />
                <xs:element name="Gesamtergebnis_schriftlich" type="xs:string" minOccurs="0" />
                <xs:element name="Gesamtergebnis_muendlich" type="xs:string" minOccurs="0" />
                <xs:element name="Gesamtergebnis" type="xs:string" minOccurs="0" />
                <xs:element name="Note" type="xs:string" minOccurs="0" />
                <xs:element name="Geburtsdatum" type="xs:string" minOccurs="0" />
                <xs:element name="Pruefungsdatum" type="xs:dateTime" minOccurs="0" />
              </xs:sequence>
            </xs:complexType>
          </xs:element>
        </xs:choice>
      </xs:complexType>
    </xs:element>
  </xs:schema>
  <Table><Stapel>0</Stapel><Name>KALKAN</Name><Vorname>ASLIHAN</Vorname><Geburtsort>KAYNARCA/GÜRÜN</Geburtsort><Bogennummer>D156849</Bogennummer><Teil1_schriftlich>75</Teil1_schriftlich><Teil2_schriftlich>27</Teil2_schriftlich><Teil3_schriftlich>52.5</Teil3_schriftlich><Teil4_schriftlich>27</Teil4_schriftlich><BewertSchriftlich></BewertSchriftlich><Teil1_muendlich>15</Teil1_muendlich><Teil2_muendlich>28</Teil2_muendlich><Teil3_muendlich>26</Teil3_muendlich><Teil4_muendlich>0.00</Teil4_muendlich><Teil5_muendlich>0.00</Teil5_muendlich><BewertMuendlich></BewertMuendlich><Gesamtergebnis_schriftlich>181.5</Gesamtergebnis_schriftlich><Gesamtergebnis_muendlich>69</Gesamtergebnis_muendlich><Gesamtergebnis>250.5</Gesamtergebnis><Note>2</Note><Geburtsdatum>1985-02-07 00:00:00</Geburtsdatum><Pruefungsdatum>2024-07-04T07:00:00+00:00</Pruefungsdatum></Table><Table><Stapel>0</Stapel><Name>ÇOBAN</Name><Vorname>AYŞE DURDU</Vorname><Geburtsort>MUT</Geburtsort><Bogennummer>D156852</Bogennummer><Teil1_schriftlich>35</Teil1_schriftlich><Teil2_schriftlich>13.5</Teil2_schriftlich><Teil3_schriftlich>42.5</Teil3_schriftlich><Teil4_schriftlich>9</Teil4_schriftlich><BewertSchriftlich></BewertSchriftlich><Teil1_muendlich>10</Teil1_muendlich><Teil2_muendlich>18</Teil2_muendlich><Teil3_muendlich>18</Teil3_muendlich><Teil4_muendlich>0.00</Teil4_muendlich><Teil5_muendlich>0.00</Teil5_muendlich><BewertMuendlich></BewertMuendlich><Gesamtergebnis_schriftlich>100</Gesamtergebnis_schriftlich><Gesamtergebnis_muendlich>46</Gesamtergebnis_muendlich><Gesamtergebnis>146</Gesamtergebnis><Note>F</Note><Geburtsdatum>2006-01-28 00:00:00</Geburtsdatum><Pruefungsdatum>2024-07-04T07:00:00+00:00</Pruefungsdatum></Table><Table><Stapel>0</Stapel><Name>HÜYÜK</Name><Vorname>ZUHAL</Vorname><Geburtsort>DÜZCE</Geburtsort><Bogennummer>D156854</Bogennummer><Teil1_schriftlich>40</Teil1_schriftlich><Teil2_schriftlich>15</Teil2_schriftlich><Teil3_schriftlich>45</Teil3_schriftlich><Teil4_schriftlich>27</Teil4_schriftlich><BewertSchriftlich></BewertSchriftlich><Teil1_muendlich>13</Teil1_muendlich><Teil2_muendlich>20</Teil2_muendlich><Teil3_muendlich>18</Teil3_muendlich><Teil4_muendlich>0.00</Teil4_muendlich><Teil5_muendlich>0.00</Teil5_muendlich><BewertMuendlich></BewertMuendlich><Gesamtergebnis_schriftlich>127</Gesamtergebnis_schriftlich><Gesamtergebnis_muendlich>51</Gesamtergebnis_muendlich><Gesamtergebnis>178</Gesamtergebnis><Note>F</Note><Geburtsdatum>1985-01-13 00:00:00</Geburtsdatum><Pruefungsdatum>2024-07-04T07:00:00+00:00</Pruefungsdatum></Table><Table><Stapel>0</Stapel><Name>MODİRİ DİLEK</Name><Vorname>IŞIL GÜNEŞ</Vorname><Geburtsort>İLKADIM/SAMSUN</Geburtsort><Bogennummer>D156853</Bogennummer><Teil1_schriftlich>40</Teil1_schriftlich><Teil2_schriftlich>9</Teil2_schriftlich><Teil3_schriftlich>45</Teil3_schriftlich><Teil4_schriftlich>21</Teil4_schriftlich><BewertSchriftlich></BewertSchriftlich><Teil1_muendlich>10</Teil1_muendlich><Teil2_muendlich>18</Teil2_muendlich><Teil3_muendlich>18</Teil3_muendlich><Teil4_muendlich>0.00</Teil4_muendlich><Teil5_muendlich>0.00</Teil5_muendlich><BewertMuendlich></BewertMuendlich><Gesamtergebnis_schriftlich>115</Gesamtergebnis_schriftlich><Gesamtergebnis_muendlich>46</Gesamtergebnis_muendlich><Gesamtergebnis>161</Gesamtergebnis><Note>F</Note><Geburtsdatum>1977-06-19 00:00:00</Geburtsdatum><Pruefungsdatum>2024-07-04T07:00:00+00:00</Pruefungsdatum></Table><Table><Stapel>0</Stapel><Name>KOÇYİĞİT</Name><Vorname>VOLKAN</Vorname><Geburtsort>ALTINDAĞ</Geburtsort><Bogennummer>D156855</Bogennummer><Teil1_schriftlich>55</Teil1_schriftlich><Teil2_schriftlich>16.5</Teil2_schriftlich><Teil3_schriftlich>50</Teil3_schriftlich><Teil4_schriftlich>27</Teil4_schriftlich><BewertSchriftlich></BewertSchriftlich><Teil1_muendlich>12</Teil1_muendlich><Teil2_muendlich>10</Teil2_muendlich><Teil3_muendlich>18</Teil3_muendlich><Teil4_muendlich>0.00</Teil4_muendlich><Teil5_muendlich>0.00</Teil5_muendlich><BewertMuendlich></BewertMuendlich><Gesamtergebnis_schriftlich>148.5</Gesamtergebnis_schriftlich><Gesamtergebnis_muendlich>40</Gesamtergebnis_muendlich><Gesamtergebnis>188.5</Gesamtergebnis><Note>F</Note><Geburtsdatum>1993-05-20 00:00:00</Geburtsdatum><Pruefungsdatum>2024-07-04T07:00:00+00:00</Pruefungsdatum></Table><Table><Stapel>0</Stapel><Name>UĞURCAN</Name><Vorname>ÇAĞLAR</Vorname><Geburtsort>ALTINDAĞ</Geburtsort><Bogennummer>D156856</Bogennummer><Teil1_schriftlich>50</Teil1_schriftlich><Teil2_schriftlich>9</Teil2_schriftlich><Teil3_schriftlich>52.5</Teil3_schriftlich><Teil4_schriftlich>21</Teil4_schriftlich><BewertSchriftlich></BewertSchriftlich><Teil1_muendlich>13</Teil1_muendlich><Teil2_muendlich>18</Teil2_muendlich><Teil3_muendlich>16</Teil3_muendlich><Teil4_muendlich>0.00</Teil4_muendlich><Teil5_muendlich>0.00</Teil5_muendlich><BewertMuendlich></BewertMuendlich><Gesamtergebnis_schriftlich>132.5</Gesamtergebnis_schriftlich><Gesamtergebnis_muendlich>47</Gesamtergebnis_muendlich><Gesamtergebnis>179.5</Gesamtergebnis><Note>F</Note><Geburtsdatum>1994-06-12 00:00:00</Geburtsdatum><Pruefungsdatum>2024-07-04T07:00:00+00:00</Pruefungsdatum></Table><Table><Stapel>0</Stapel><Name>NASHVANOVA</Name><Vorname>FARANGIZ</Vorname><Geburtsort>TASHKENT</Geburtsort><Bogennummer>D156857</Bogennummer><Teil1_schriftlich>35</Teil1_schriftlich><Teil2_schriftlich>19.5</Teil2_schriftlich><Teil3_schriftlich>52.5</Teil3_schriftlich><Teil4_schriftlich>21</Teil4_schriftlich><BewertSchriftlich></BewertSchriftlich><Teil1_muendlich>0.00</Teil1_muendlich><Teil2_muendlich>0.00</Teil2_muendlich><Teil3_muendlich>0.00</Teil3_muendlich><Teil4_muendlich>0.00</Teil4_muendlich><Teil5_muendlich>0.00</Teil5_muendlich><BewertMuendlich></BewertMuendlich><Gesamtergebnis_schriftlich>128</Gesamtergebnis_schriftlich><Gesamtergebnis_muendlich>48</Gesamtergebnis_muendlich><Gesamtergebnis>176</Gesamtergebnis><Note>F</Note><Geburtsdatum>1998-04-29 00:00:00</Geburtsdatum><Pruefungsdatum>2024-07-04T07:00:00+00:00</Pruefungsdatum></Table><Table><Stapel>0</Stapel><Name>MUSTAĞNİ</Name><Vorname>MEHMET</Vorname><Geburtsort>ANTAKYA</Geburtsort><Bogennummer>D156858</Bogennummer><Teil1_schriftlich>37.5</Teil1_schriftlich><Teil2_schriftlich>12</Teil2_schriftlich><Teil3_schriftlich>50</Teil3_schriftlich><Teil4_schriftlich>27</Teil4_schriftlich><BewertSchriftlich></BewertSchriftlich><Teil1_muendlich>14</Teil1_muendlich><Teil2_muendlich>20</Teil2_muendlich><Teil3_muendlich>0</Teil3_muendlich><Teil4_muendlich>0.00</Teil4_muendlich><Teil5_muendlich>0.00</Teil5_muendlich><BewertMuendlich></BewertMuendlich><Gesamtergebnis_schriftlich>126.5</Gesamtergebnis_schriftlich><Gesamtergebnis_muendlich>34</Gesamtergebnis_muendlich><Gesamtergebnis>160.5</Gesamtergebnis><Note>F</Note><Geburtsdatum>1996-05-31 00:00:00</Geburtsdatum><Pruefungsdatum>2024-07-04T07:00:00+00:00</Pruefungsdatum></Table><Table><Stapel>0</Stapel><Name>ŞİMŞEK</Name><Vorname>SEDEF</Vorname><Geburtsort>LAÇİN</Geburtsort><Bogennummer>D156848</Bogennummer><Teil1_schriftlich>60</Teil1_schriftlich><Teil2_schriftlich>24</Teil2_schriftlich><Teil3_schriftlich>50</Teil3_schriftlich><Teil4_schriftlich>21</Teil4_schriftlich><BewertSchriftlich></BewertSchriftlich><Teil1_muendlich>13</Teil1_muendlich><Teil2_muendlich>14</Teil2_muendlich><Teil3_muendlich>20</Teil3_muendlich><Teil4_muendlich>0.00</Teil4_muendlich><Teil5_muendlich>0.00</Teil5_muendlich><BewertMuendlich></BewertMuendlich><Gesamtergebnis_schriftlich>155</Gesamtergebnis_schriftlich><Gesamtergebnis_muendlich>47</Gesamtergebnis_muendlich><Gesamtergebnis>202</Gesamtergebnis><Note>4</Note><Geburtsdatum>1998-09-19 00:00:00</Geburtsdatum><Pruefungsdatum>2024-07-04T07:00:00+00:00</Pruefungsdatum></Table><Table><Stapel>0</Stapel><Name>ASLAN</Name><Vorname>BENAY</Vorname><Geburtsort>ANTAKYA</Geburtsort><Bogennummer>D156850</Bogennummer><Teil1_schriftlich>42.5</Teil1_schriftlich><Teil2_schriftlich>18</Teil2_schriftlich><Teil3_schriftlich>47.5</Teil3_schriftlich><Teil4_schriftlich>27</Teil4_schriftlich><BewertSchriftlich></BewertSchriftlich><Teil1_muendlich>14</Teil1_muendlich><Teil2_muendlich>20</Teil2_muendlich><Teil3_muendlich>22</Teil3_muendlich><Teil4_muendlich>0.00</Teil4_muendlich><Teil5_muendlich>0.00</Teil5_muendlich><BewertMuendlich></BewertMuendlich><Gesamtergebnis_schriftlich>135</Gesamtergebnis_schriftlich><Gesamtergebnis_muendlich>56</Gesamtergebnis_muendlich><Gesamtergebnis>191</Gesamtergebnis><Note>4</Note><Geburtsdatum>2003-05-20 00:00:00</Geburtsdatum><Pruefungsdatum>2024-07-04T07:00:00+00:00</Pruefungsdatum></Table><Table><Stapel>0</Stapel><Name>SİNAN</Name><Vorname>YILDIRAY GÖRKEM</Vorname><Geburtsort>MUT</Geburtsort><Bogennummer>D156851</Bogennummer><Teil1_schriftlich>67.5</Teil1_schriftlich><Teil2_schriftlich>27</Teil2_schriftlich><Teil3_schriftlich>67.5</Teil3_schriftlich><Teil4_schriftlich>39</Teil4_schriftlich><BewertSchriftlich></BewertSchriftlich><Teil1_muendlich>13</Teil1_muendlich><Teil2_muendlich>28</Teil2_muendlich><Teil3_muendlich>28</Teil3_muendlich><Teil4_muendlich>0.00</Teil4_muendlich><Teil5_muendlich>0.00</Teil5_muendlich><BewertMuendlich></BewertMuendlich><Gesamtergebnis_schriftlich>201</Gesamtergebnis_schriftlich><Gesamtergebnis_muendlich>69</Gesamtergebnis_muendlich><Gesamtergebnis>270</Gesamtergebnis><Note>1</Note><Geburtsdatum>2006-02-03 00:00:00</Geburtsdatum><Pruefungsdatum>2024-07-04T07:00:00+00:00</Pruefungsdatum></Table>
</NewDataSet>